UIBotPy/__init__.py
UIBotPy/__main__.py
UIBotPy-0.0.1.dist-info/METADATA
UIBotPy-0.0.1.dist-info/WHEEL
UIBotPy-0.0.1.dist-info/top_level.txt
UIBotPy-0.0.1.dist-info/RECORD
