Metadata-Version: 2.1
Name: UIBotPy
Version: 0.0.1
Summary: UI Automation
Home-page: https://github.com/you/your_package_repo
Author: Valdemar Petersen
Author-email: valdemarlpt@gmail.com
Classifier: Programming Language :: Python :: 3.7
Classifier: Operating System :: OS Independent
